{
    "os": "Linux-5.4.204-ql-generic-12.0-19-x86_64-with-glibc2.31",
    "python": "3.10.12",
    "heartbeatAt": "2024-04-10T14:28:49.585165",
    "startedAt": "2024-04-10T14:28:48.687840",
    "docker": null,
    "cuda": null,
    "args": [
        "--output_dir=/l/users/abdelrahman.sadallah/UWFE-Mixtral",
        "--model_name_or_path=mistralai/Mistral-7B-v0.1",
        "--wandb_project=nlp804-UWFE-Mixtral",
        "--dataset",
        "boda/kaneko_data",
        "--evaluation_strategy",
        "steps",
        "--num_train_epochs=10",
        "--save_steps=10",
        "--eval_steps=10",
        "--logging_steps=10",
        "--report_to=all",
        "--load_best_model_at_end",
        "True",
        "--save_total_limit",
        "3",
        "--per_device_train_batch_size=8",
        "--per_device_eval_batch_size=8",
        "--metric_for_best_model",
        "accuracy",
        "--warmup_ratio=0.07",
        "--weight_decay=0.01",
        "--learning_rate=1e-06",
        "--use_flash_attention_2=True",
        "--prompt_key=prompt",
        "--num_shots",
        "0",
        "--explicit_errors",
        "0"
    ],
    "state": "running",
    "program": "/home/abdelrahman.sadallah/mbzuai/UWFe/finetune.py",
    "codePathLocal": "finetune.py",
    "codePath": "finetune.py",
    "git": {
        "remote": "git@github.com:BodaSadalla98/UWFe.git",
        "commit": "87dbc679087c78ed2dc55dbead69850a73f2d575"
    },
    "email": "boda998@yahoo.com",
    "root": "/home/abdelrahman.sadallah/mbzuai/UWFe",
    "host": "gpu-09",
    "username": "abdelrahman.sadallah",
    "executable": "/home/abdelrahman.sadallah/mambaforge/envs/nlp/bin/python",
    "cpu_count": 128,
    "cpu_count_logical": 256,
    "cpu_freq": {
        "current": 1854.7102265625006,
        "min": 1500.0,
        "max": 2250.0
    },
    "cpu_freq_per_core": [
        {
            "current": 1369.047,
            "min": 1500.0,
            "max": 2250.0
        },
        {
            "current": 1374.732,
            "min": 1500.0,
            "max": 2250.0
        },
        {
            "current": 1372.928,
            "min": 1500.0,
            "max": 2250.0
        },
        {
            "current": 2923.509,
            "min": 1500.0,
            "max": 2250.0
        },
        {
            "current": 1499.825,
            "min": 1500.0,
            "max": 2250.0
        },
        {
            "current": 1499.862,
            "min": 1500.0,
            "max": 2250.0
        },
        {
            "current": 1499.94,
            "min": 1500.0,
            "max": 2250.0
        },
        {
            "current": 1499.905,
            "min": 1500.0,
            "max": 2250.0
        },
        {
            "current": 1499.937,
            "min": 1500.0,
            "max": 2250.0
        },
        {
            "current": 1499.923,
            "min": 1500.0,
            "max": 2250.0
        },
        {
            "current": 1499.876,
            "min": 1500.0,
            "max": 2250.0
        },
        {
            "current": 1499.871,
            "min": 1500.0,
            "max": 2250.0
        },
        {
            "current": 1499.968,
            "min": 1500.0,
            "max": 2250.0
        },
        {
            "current": 1499.938,
            "min": 1500.0,
            "max": 2250.0
        },
        {
            "current": 1499.959,
            "min": 1500.0,
            "max": 2250.0
        },
        {
            "current": 1499.704,
            "min": 1500.0,
            "max": 2250.0
        },
        {
            "current": 1499.906,
            "min": 1500.0,
            "max": 2250.0
        },
        {
            "current": 1499.882,
            "min": 1500.0,
            "max": 2250.0
        },
        {
            "current": 1499.627,
            "min": 1500.0,
            "max": 2250.0
        },
        {
            "current": 1499.933,
            "min": 1500.0,
            "max": 2250.0
        },
        {
            "current": 1499.951,
            "min": 1500.0,
            "max": 2250.0
        },
        {
            "current": 1499.852,
            "min": 1500.0,
            "max": 2250.0
        },
        {
            "current": 1499.864,
            "min": 1500.0,
            "max": 2250.0
        },
        {
            "current": 1499.823,
            "min": 1500.0,
            "max": 2250.0
        },
        {
            "current": 1499.903,
            "min": 1500.0,
            "max": 2250.0
        },
        {
            "current": 1499.865,
            "min": 1500.0,
            "max": 2250.0
        },
        {
            "current": 1499.902,
            "min": 1500.0,
            "max": 2250.0
        },
        {
            "current": 1499.892,
            "min": 1500.0,
            "max": 2250.0
        },
        {
            "current": 1499.055,
            "min": 1500.0,
            "max": 2250.0
        },
        {
            "current": 1499.827,
            "min": 1500.0,
            "max": 2250.0
        },
        {
            "current": 1499.909,
            "min": 1500.0,
            "max": 2250.0
        },
        {
            "current": 1499.77,
            "min": 1500.0,
            "max": 2250.0
        },
        {
            "current": 1499.826,
            "min": 1500.0,
            "max": 2250.0
        },
        {
            "current": 1499.704,
            "min": 1500.0,
            "max": 2250.0
        },
        {
            "current": 1499.798,
            "min": 1500.0,
            "max": 2250.0
        },
        {
            "current": 1499.905,
            "min": 1500.0,
            "max": 2250.0
        },
        {
            "current": 1499.905,
            "min": 1500.0,
            "max": 2250.0
        },
        {
            "current": 1499.871,
            "min": 1500.0,
            "max": 2250.0
        },
        {
            "current": 1499.773,
            "min": 1500.0,
            "max": 2250.0
        },
        {
            "current": 1499.966,
            "min": 1500.0,
            "max": 2250.0
        },
        {
            "current": 1499.952,
            "min": 1500.0,
            "max": 2250.0
        },
        {
            "current": 1499.978,
            "min": 1500.0,
            "max": 2250.0
        },
        {
            "current": 1499.821,
            "min": 1500.0,
            "max": 2250.0
        },
        {
            "current": 1499.812,
            "min": 1500.0,
            "max": 2250.0
        },
        {
            "current": 1499.83,
            "min": 1500.0,
            "max": 2250.0
        },
        {
            "current": 1496.173,
            "min": 1500.0,
            "max": 2250.0
        },
        {
            "current": 1497.865,
            "min": 1500.0,
            "max": 2250.0
        },
        {
            "current": 1499.827,
            "min": 1500.0,
            "max": 2250.0
        },
        {
            "current": 1499.737,
            "min": 1500.0,
            "max": 2250.0
        },
        {
            "current": 1499.794,
            "min": 1500.0,
            "max": 2250.0
        },
        {
            "current": 1498.961,
            "min": 1500.0,
            "max": 2250.0
        },
        {
            "current": 1498.886,
            "min": 1500.0,
            "max": 2250.0
        },
        {
            "current": 1498.876,
            "min": 1500.0,
            "max": 2250.0
        },
        {
            "current": 1498.89,
            "min": 1500.0,
            "max": 2250.0
        },
        {
            "current": 1498.883,
            "min": 1500.0,
            "max": 2250.0
        },
        {
            "current": 1498.893,
            "min": 1500.0,
            "max": 2250.0
        },
        {
            "current": 1497.724,
            "min": 1500.0,
            "max": 2250.0
        },
        {
            "current": 1497.834,
            "min": 1500.0,
            "max": 2250.0
        },
        {
            "current": 1497.861,
            "min": 1500.0,
            "max": 2250.0
        },
        {
            "current": 1497.821,
            "min": 1500.0,
            "max": 2250.0
        },
        {
            "current": 1507.975,
            "min": 1500.0,
            "max": 2250.0
        },
        {
            "current": 1841.486,
            "min": 1500.0,
            "max": 2250.0
        },
        {
            "current": 1508.061,
            "min": 1500.0,
            "max": 2250.0
        },
        {
            "current": 3383.853,
            "min": 1500.0,
            "max": 2250.0
        },
        {
            "current": 1510.983,
            "min": 1500.0,
            "max": 2250.0
        },
        {
            "current": 3400.199,
            "min": 1500.0,
            "max": 2250.0
        },
        {
            "current": 1510.994,
            "min": 1500.0,
            "max": 2250.0
        },
        {
            "current": 1510.972,
            "min": 1500.0,
            "max": 2250.0
        },
        {
            "current": 3399.745,
            "min": 1500.0,
            "max": 2250.0
        },
        {
            "current": 1511.004,
            "min": 1500.0,
            "max": 2250.0
        },
        {
            "current": 1511.048,
            "min": 1500.0,
            "max": 2250.0
        },
        {
            "current": 1511.121,
            "min": 1500.0,
            "max": 2250.0
        },
        {
            "current": 1498.408,
            "min": 1500.0,
            "max": 2250.0
        },
        {
            "current": 1498.374,
            "min": 1500.0,
            "max": 2250.0
        },
        {
            "current": 1498.341,
            "min": 1500.0,
            "max": 2250.0
        },
        {
            "current": 1498.44,
            "min": 1500.0,
            "max": 2250.0
        },
        {
            "current": 1499.449,
            "min": 1500.0,
            "max": 2250.0
        },
        {
            "current": 1499.493,
            "min": 1500.0,
            "max": 2250.0
        },
        {
            "current": 1499.947,
            "min": 1500.0,
            "max": 2250.0
        },
        {
            "current": 1499.842,
            "min": 1500.0,
            "max": 2250.0
        },
        {
            "current": 1554.738,
            "min": 1500.0,
            "max": 2250.0
        },
        {
            "current": 1478.285,
            "min": 1500.0,
            "max": 2250.0
        },
        {
            "current": 1496.221,
            "min": 1500.0,
            "max": 2250.0
        },
        {
            "current": 1477.946,
            "min": 1500.0,
            "max": 2250.0
        },
        {
            "current": 1498.965,
            "min": 1500.0,
            "max": 2250.0
        },
        {
            "current": 1498.819,
            "min": 1500.0,
            "max": 2250.0
        },
        {
            "current": 1498.977,
            "min": 1500.0,
            "max": 2250.0
        },
        {
            "current": 1498.955,
            "min": 1500.0,
            "max": 2250.0
        },
        {
            "current": 1498.402,
            "min": 1500.0,
            "max": 2250.0
        },
        {
            "current": 1498.385,
            "min": 1500.0,
            "max": 2250.0
        },
        {
            "current": 1498.37,
            "min": 1500.0,
            "max": 2250.0
        },
        {
            "current": 1498.435,
            "min": 1500.0,
            "max": 2250.0
        },
        {
            "current": 1499.484,
            "min": 1500.0,
            "max": 2250.0
        },
        {
            "current": 1499.993,
            "min": 1500.0,
            "max": 2250.0
        },
        {
            "current": 1499.493,
            "min": 1500.0,
            "max": 2250.0
        },
        {
            "current": 1499.421,
            "min": 1500.0,
            "max": 2250.0
        },
        {
            "current": 1500.061,
            "min": 1500.0,
            "max": 2250.0
        },
        {
            "current": 1500.064,
            "min": 1500.0,
            "max": 2250.0
        },
        {
            "current": 1499.993,
            "min": 1500.0,
            "max": 2250.0
        },
        {
            "current": 1500.062,
            "min": 1500.0,
            "max": 2250.0
        },
        {
            "current": 1479.373,
            "min": 1500.0,
            "max": 2250.0
        },
        {
            "current": 1558.652,
            "min": 1500.0,
            "max": 2250.0
        },
        {
            "current": 1559.405,
            "min": 1500.0,
            "max": 2250.0
        },
        {
            "current": 1559.311,
            "min": 1500.0,
            "max": 2250.0
        },
        {
            "current": 1499.387,
            "min": 1500.0,
            "max": 2250.0
        },
        {
            "current": 1499.48,
            "min": 1500.0,
            "max": 2250.0
        },
        {
            "current": 1499.425,
            "min": 1500.0,
            "max": 2250.0
        },
        {
            "current": 1499.929,
            "min": 1500.0,
            "max": 2250.0
        },
        {
            "current": 1499.938,
            "min": 1500.0,
            "max": 2250.0
        },
        {
            "current": 1499.622,
            "min": 1500.0,
            "max": 2250.0
        },
        {
            "current": 1499.777,
            "min": 1500.0,
            "max": 2250.0
        },
        {
            "current": 1499.862,
            "min": 1500.0,
            "max": 2250.0
        },
        {
            "current": 1499.694,
            "min": 1500.0,
            "max": 2250.0
        },
        {
            "current": 1499.861,
            "min": 1500.0,
            "max": 2250.0
        },
        {
            "current": 1499.521,
            "min": 1500.0,
            "max": 2250.0
        },
        {
            "current": 1499.888,
            "min": 1500.0,
            "max": 2250.0
        },
        {
            "current": 1499.827,
            "min": 1500.0,
            "max": 2250.0
        },
        {
            "current": 1499.828,
            "min": 1500.0,
            "max": 2250.0
        },
        {
            "current": 1499.792,
            "min": 1500.0,
            "max": 2250.0
        },
        {
            "current": 1499.844,
            "min": 1500.0,
            "max": 2250.0
        },
        {
            "current": 1499.827,
            "min": 1500.0,
            "max": 2250.0
        },
        {
            "current": 1499.825,
            "min": 1500.0,
            "max": 2250.0
        },
        {
            "current": 1499.864,
            "min": 1500.0,
            "max": 2250.0
        },
        {
            "current": 1499.85,
            "min": 1500.0,
            "max": 2250.0
        },
        {
            "current": 1499.917,
            "min": 1500.0,
            "max": 2250.0
        },
        {
            "current": 1500.169,
            "min": 1500.0,
            "max": 2250.0
        },
        {
            "current": 1500.061,
            "min": 1500.0,
            "max": 2250.0
        },
        {
            "current": 1500.054,
            "min": 1500.0,
            "max": 2250.0
        },
        {
            "current": 1369.826,
            "min": 1500.0,
            "max": 2250.0
        },
        {
            "current": 1374.018,
            "min": 1500.0,
            "max": 2250.0
        },
        {
            "current": 1375.835,
            "min": 1500.0,
            "max": 2250.0
        },
        {
            "current": 2116.244,
            "min": 1500.0,
            "max": 2250.0
        },
        {
            "current": 1499.719,
            "min": 1500.0,
            "max": 2250.0
        },
        {
            "current": 1499.895,
            "min": 1500.0,
            "max": 2250.0
        },
        {
            "current": 1499.927,
            "min": 1500.0,
            "max": 2250.0
        },
        {
            "current": 1499.824,
            "min": 1500.0,
            "max": 2250.0
        },
        {
            "current": 1499.962,
            "min": 1500.0,
            "max": 2250.0
        },
        {
            "current": 1499.987,
            "min": 1500.0,
            "max": 2250.0
        },
        {
            "current": 1499.932,
            "min": 1500.0,
            "max": 2250.0
        },
        {
            "current": 1499.971,
            "min": 1500.0,
            "max": 2250.0
        },
        {
            "current": 1500.037,
            "min": 1500.0,
            "max": 2250.0
        },
        {
            "current": 1499.981,
            "min": 1500.0,
            "max": 2250.0
        },
        {
            "current": 1499.902,
            "min": 1500.0,
            "max": 2250.0
        },
        {
            "current": 1499.91,
            "min": 1500.0,
            "max": 2250.0
        },
        {
            "current": 1499.981,
            "min": 1500.0,
            "max": 2250.0
        },
        {
            "current": 1500.065,
            "min": 1500.0,
            "max": 2250.0
        },
        {
            "current": 1499.995,
            "min": 1500.0,
            "max": 2250.0
        },
        {
            "current": 1500.013,
            "min": 1500.0,
            "max": 2250.0
        },
        {
            "current": 1499.992,
            "min": 1500.0,
            "max": 2250.0
        },
        {
            "current": 1499.969,
            "min": 1500.0,
            "max": 2250.0
        },
        {
            "current": 1499.877,
            "min": 1500.0,
            "max": 2250.0
        },
        {
            "current": 1499.995,
            "min": 1500.0,
            "max": 2250.0
        },
        {
            "current": 1499.949,
            "min": 1500.0,
            "max": 2250.0
        },
        {
            "current": 1499.964,
            "min": 1500.0,
            "max": 2250.0
        },
        {
            "current": 1500.034,
            "min": 1500.0,
            "max": 2250.0
        },
        {
            "current": 1499.918,
            "min": 1500.0,
            "max": 2250.0
        },
        {
            "current": 1499.035,
            "min": 1500.0,
            "max": 2250.0
        },
        {
            "current": 1499.901,
            "min": 1500.0,
            "max": 2250.0
        },
        {
            "current": 1499.335,
            "min": 1500.0,
            "max": 2250.0
        },
        {
            "current": 1499.868,
            "min": 1500.0,
            "max": 2250.0
        },
        {
            "current": 1499.89,
            "min": 1500.0,
            "max": 2250.0
        },
        {
            "current": 1499.785,
            "min": 1500.0,
            "max": 2250.0
        },
        {
            "current": 1499.902,
            "min": 1500.0,
            "max": 2250.0
        },
        {
            "current": 1499.826,
            "min": 1500.0,
            "max": 2250.0
        },
        {
            "current": 1499.905,
            "min": 1500.0,
            "max": 2250.0
        },
        {
            "current": 1499.892,
            "min": 1500.0,
            "max": 2250.0
        },
        {
            "current": 1499.942,
            "min": 1500.0,
            "max": 2250.0
        },
        {
            "current": 1499.959,
            "min": 1500.0,
            "max": 2250.0
        },
        {
            "current": 1499.875,
            "min": 1500.0,
            "max": 2250.0
        },
        {
            "current": 1499.928,
            "min": 1500.0,
            "max": 2250.0
        },
        {
            "current": 1499.821,
            "min": 1500.0,
            "max": 2250.0
        },
        {
            "current": 1499.939,
            "min": 1500.0,
            "max": 2250.0
        },
        {
            "current": 1499.917,
            "min": 1500.0,
            "max": 2250.0
        },
        {
            "current": 1499.838,
            "min": 1500.0,
            "max": 2250.0
        },
        {
            "current": 1499.91,
            "min": 1500.0,
            "max": 2250.0
        },
        {
            "current": 1499.904,
            "min": 1500.0,
            "max": 2250.0
        },
        {
            "current": 1499.867,
            "min": 1500.0,
            "max": 2250.0
        },
        {
            "current": 1499.859,
            "min": 1500.0,
            "max": 2250.0
        },
        {
            "current": 1499.088,
            "min": 1500.0,
            "max": 2250.0
        },
        {
            "current": 1499.03,
            "min": 1500.0,
            "max": 2250.0
        },
        {
            "current": 1499.012,
            "min": 1500.0,
            "max": 2250.0
        },
        {
            "current": 1499.013,
            "min": 1500.0,
            "max": 2250.0
        },
        {
            "current": 1498.929,
            "min": 1500.0,
            "max": 2250.0
        },
        {
            "current": 1498.843,
            "min": 1500.0,
            "max": 2250.0
        },
        {
            "current": 1497.987,
            "min": 1500.0,
            "max": 2250.0
        },
        {
            "current": 1498.088,
            "min": 1500.0,
            "max": 2250.0
        },
        {
            "current": 1498.09,
            "min": 1500.0,
            "max": 2250.0
        },
        {
            "current": 1498.072,
            "min": 1500.0,
            "max": 2250.0
        },
        {
            "current": 1488.105,
            "min": 1500.0,
            "max": 2250.0
        },
        {
            "current": 1878.611,
            "min": 1500.0,
            "max": 2250.0
        },
        {
            "current": 1488.257,
            "min": 1500.0,
            "max": 2250.0
        },
        {
            "current": 3225.67,
            "min": 1500.0,
            "max": 2250.0
        },
        {
            "current": 1510.947,
            "min": 1500.0,
            "max": 2250.0
        },
        {
            "current": 3396.154,
            "min": 1500.0,
            "max": 2250.0
        },
        {
            "current": 1510.968,
            "min": 1500.0,
            "max": 2250.0
        },
        {
            "current": 1511.029,
            "min": 1500.0,
            "max": 2250.0
        },
        {
            "current": 3396.214,
            "min": 1500.0,
            "max": 2250.0
        },
        {
            "current": 1511.097,
            "min": 1500.0,
            "max": 2250.0
        },
        {
            "current": 1511.038,
            "min": 1500.0,
            "max": 2250.0
        },
        {
            "current": 1510.979,
            "min": 1500.0,
            "max": 2250.0
        },
        {
            "current": 1499.572,
            "min": 1500.0,
            "max": 2250.0
        },
        {
            "current": 1498.563,
            "min": 1500.0,
            "max": 2250.0
        },
        {
            "current": 1498.532,
            "min": 1500.0,
            "max": 2250.0
        },
        {
            "current": 1498.609,
            "min": 1500.0,
            "max": 2250.0
        },
        {
            "current": 1499.522,
            "min": 1500.0,
            "max": 2250.0
        },
        {
            "current": 1499.556,
            "min": 1500.0,
            "max": 2250.0
        },
        {
            "current": 1499.548,
            "min": 1500.0,
            "max": 2250.0
        },
        {
            "current": 1499.529,
            "min": 1500.0,
            "max": 2250.0
        },
        {
            "current": 1604.578,
            "min": 1500.0,
            "max": 2250.0
        },
        {
            "current": 1462.338,
            "min": 1500.0,
            "max": 2250.0
        },
        {
            "current": 1462.244,
            "min": 1500.0,
            "max": 2250.0
        },
        {
            "current": 1462.198,
            "min": 1500.0,
            "max": 2250.0
        },
        {
            "current": 1499.083,
            "min": 1500.0,
            "max": 2250.0
        },
        {
            "current": 1498.966,
            "min": 1500.0,
            "max": 2250.0
        },
        {
            "current": 1499.065,
            "min": 1500.0,
            "max": 2250.0
        },
        {
            "current": 1499.085,
            "min": 1500.0,
            "max": 2250.0
        },
        {
            "current": 1498.586,
            "min": 1500.0,
            "max": 2250.0
        },
        {
            "current": 1498.579,
            "min": 1500.0,
            "max": 2250.0
        },
        {
            "current": 1498.555,
            "min": 1500.0,
            "max": 2250.0
        },
        {
            "current": 1498.584,
            "min": 1500.0,
            "max": 2250.0
        },
        {
            "current": 1499.555,
            "min": 1500.0,
            "max": 2250.0
        },
        {
            "current": 1499.495,
            "min": 1500.0,
            "max": 2250.0
        },
        {
            "current": 1499.526,
            "min": 1500.0,
            "max": 2250.0
        },
        {
            "current": 1499.486,
            "min": 1500.0,
            "max": 2250.0
        },
        {
            "current": 1500.031,
            "min": 1500.0,
            "max": 2250.0
        },
        {
            "current": 1500.061,
            "min": 1500.0,
            "max": 2250.0
        },
        {
            "current": 1500.003,
            "min": 1500.0,
            "max": 2250.0
        },
        {
            "current": 1500.065,
            "min": 1500.0,
            "max": 2250.0
        },
        {
            "current": 1493.366,
            "min": 1500.0,
            "max": 2250.0
        },
        {
            "current": 1608.127,
            "min": 1500.0,
            "max": 2250.0
        },
        {
            "current": 1608.126,
            "min": 1500.0,
            "max": 2250.0
        },
        {
            "current": 1608.193,
            "min": 1500.0,
            "max": 2250.0
        },
        {
            "current": 1499.459,
            "min": 1500.0,
            "max": 2250.0
        },
        {
            "current": 1499.548,
            "min": 1500.0,
            "max": 2250.0
        },
        {
            "current": 1499.487,
            "min": 1500.0,
            "max": 2250.0
        },
        {
            "current": 1499.55,
            "min": 1500.0,
            "max": 2250.0
        },
        {
            "current": 1500.019,
            "min": 1500.0,
            "max": 2250.0
        },
        {
            "current": 1499.795,
            "min": 1500.0,
            "max": 2250.0
        },
        {
            "current": 1499.74,
            "min": 1500.0,
            "max": 2250.0
        },
        {
            "current": 1499.801,
            "min": 1500.0,
            "max": 2250.0
        },
        {
            "current": 1499.663,
            "min": 1500.0,
            "max": 2250.0
        },
        {
            "current": 1499.391,
            "min": 1500.0,
            "max": 2250.0
        },
        {
            "current": 1499.287,
            "min": 1500.0,
            "max": 2250.0
        },
        {
            "current": 1499.712,
            "min": 1500.0,
            "max": 2250.0
        },
        {
            "current": 1499.788,
            "min": 1500.0,
            "max": 2250.0
        },
        {
            "current": 1499.779,
            "min": 1500.0,
            "max": 2250.0
        },
        {
            "current": 1499.553,
            "min": 1500.0,
            "max": 2250.0
        },
        {
            "current": 1499.759,
            "min": 1500.0,
            "max": 2250.0
        },
        {
            "current": 1499.829,
            "min": 1500.0,
            "max": 2250.0
        },
        {
            "current": 1499.715,
            "min": 1500.0,
            "max": 2250.0
        },
        {
            "current": 1499.519,
            "min": 1500.0,
            "max": 2250.0
        },
        {
            "current": 1499.595,
            "min": 1500.0,
            "max": 2250.0
        },
        {
            "current": 1499.71,
            "min": 1500.0,
            "max": 2250.0
        },
        {
            "current": 1498.525,
            "min": 1500.0,
            "max": 2250.0
        },
        {
            "current": 1499.955,
            "min": 1500.0,
            "max": 2250.0
        },
        {
            "current": 1500.057,
            "min": 1500.0,
            "max": 2250.0
        }
    ],
    "disk": {
        "/": {
            "total": 1.0,
            "used": 0.0042877197265625
        }
    },
    "gpu": "NVIDIA A100-SXM4-40GB",
    "gpu_count": 1,
    "gpu_devices": [
        {
            "name": "NVIDIA A100-SXM4-40GB",
            "memory_total": 42949672960
        }
    ],
    "memory": {
        "total": 503.78639221191406
    }
}
